bin/command_line.py
future_storage/Future-editor.png
future_storage/__init__.py
futureditor-1.0.18.dist-info/METADATA
futureditor-1.0.18.dist-info/WHEEL
futureditor-1.0.18.dist-info/entry_points.txt
futureditor-1.0.18.dist-info/top_level.txt
futureditor-1.0.18.dist-info/RECORD
