Metadata-Version: 2.1
Name: futureditor
Version: 1.0.18
Summary: code editor
Home-page: https://github.com/sanjaymarison/futureditor
Author: SanjayMarison
Author-email: sanjaymarison@gmail.com
License: MIT
Platform: UNKNOWN
Classifier: License :: OSI Approved :: MIT License
Classifier: Programming Language :: Python :: 3
Classifier: Programming Language :: Python :: 3.5
Classifier: Programming Language :: Python :: 3.6
Classifier: Programming Language :: Python :: 3.7
Classifier: Programming Language :: Python :: 3.8
Requires-Dist: pillow
